delugeClient/__init__.py
delugeClient/__main__.py
delugeClient/__version__.py
delugeClient/default_config.ini
delugeClient/deluge.py
delugeClient/deluge_socket.py
delugeClient/torrent.py
delugeClient/utils.py
delugeClient_kevin-0.3.5.dist-info/LICENSE
delugeClient_kevin-0.3.5.dist-info/METADATA
delugeClient_kevin-0.3.5.dist-info/WHEEL
delugeClient_kevin-0.3.5.dist-info/entry_points.txt
delugeClient_kevin-0.3.5.dist-info/top_level.txt
delugeClient_kevin-0.3.5.dist-info/RECORD
