Metadata-Version: 2.1
Name: delugeClient-kevin
Version: 0.3.5
Summary: Deluge client with custom functions written in python
Home-page: https://github.com/kevinmidboe/delugeClient
Author: KevinMidboe
Classifier: Programming Language :: Python
Classifier: Operating System :: OS Independent
Classifier: License :: OSI Approved :: MIT License
Classifier: Programming Language :: Python :: 3.10
Requires-Python: >=3.10
License-File: LICENSE
Requires-Dist: colored (>=1.4.4)
Requires-Dist: deluge-client (>=1.9.0)
Requires-Dist: requests (>=2.28.1)
Requires-Dist: sshtunnel (>=0.4.0)
Requires-Dist: typer[all] (>=0.7.0)
